devolve/__init__.py
devolve/registry.py
devolve-1.0.0.dist-info/DESCRIPTION.rst
devolve-1.0.0.dist-info/METADATA
devolve-1.0.0.dist-info/metadata.json
devolve-1.0.0.dist-info/RECORD
devolve-1.0.0.dist-info/top_level.txt
devolve-1.0.0.dist-info/WHEEL
