Metadata-Version: 2.0
Name: devolve
Version: 1.0.0
Summary: Callback registry
Home-page: https://github.com/simpleenergy/devolve
Author: Piper Merriam
Author-email: pipermerriam@gmail.com
License: MIT
Keywords: rest swagger
Platform: UNKNOWN
Classifier: Development Status :: 2 - Pre-Alpha
Classifier: Intended Audience :: Developers
Classifier: License :: OSI Approved :: BSD License
Classifier: Natural Language :: English
Classifier: Programming Language :: Python :: 2
Classifier: Programming Language :: Python :: 2.7
Classifier: Programming Language :: Python :: 3
Classifier: Programming Language :: Python :: 3.3
Classifier: Programming Language :: Python :: 3.4
